PyCasper-0.1.1.dev3.dist-info/DESCRIPTION.rst
PyCasper-0.1.1.dev3.dist-info/METADATA
PyCasper-0.1.1.dev3.dist-info/RECORD
PyCasper-0.1.1.dev3.dist-info/WHEEL
PyCasper-0.1.1.dev3.dist-info/metadata.json
PyCasper-0.1.1.dev3.dist-info/top_level.txt
pycasper/__init__.py
pycasper/name.py
