Metadata-Version: 2.0
Name: PyCasper
Version: 0.1.1.dev3
Summary: UNKNOWN
Home-page: https://github.com/chahuja/pycasper
Author: Chaitanya Ahuja
Author-email: ahujachaitanya@gmail.com
License: Creative Commons Attribution-Noncommercial-Share Alike license
Platform: UNKNOWN
Requires-Python: >=3
